README.rst
setup.py
javalink/__init__.py
javalink/loader.py
javalink/model.py
javalink/ref.py
sphinx_javalink.egg-info/PKG-INFO
sphinx_javalink.egg-info/SOURCES.txt
sphinx_javalink.egg-info/dependency_links.txt
sphinx_javalink.egg-info/requires.txt
sphinx_javalink.egg-info/top_level.txt