Metadata-Version: 1.1
Name: sphinx-javalink
Version: 0.11.1
Summary: Link to Javadoc APIs from Sphinx documentation
Home-page: https://github.com/bluekeyes/sphinx-javalink
Author: Billy Keyes
Author-email: bluekeyes@gmail.com
License: MIT
Keywords: javadoc java sphinx documentation
Platform: UNKNOWN
Classifier: Development Status :: 4 - Beta
Classifier: Intended Audience :: Developers
Classifier: Topic :: Documentation
Classifier: Topic :: Software Development :: Documentation
Classifier: Framework :: Sphinx :: Extension
Classifier: License :: OSI Approved :: MIT License
Classifier: Programming Language :: Java
Classifier: Programming Language :: Python :: 2
Classifier: Programming Language :: Python :: 2.7
